<?xml version="1.0" encoding="utf-8"?>
<LanguageData>

	<!-- EN: Rotti -->
	<Rotti.label>羅蒂鼠</Rotti.label>
	
	<!-- EN: A domesticated rat of unusually large size and intelligence, often kept as pets by Ratkins. -->
	<Rotti.description>一種家養的老鼠，體型和智力都比一般的老鼠更優秀。它們經常被鼠族當作寵物飼養。</Rotti.description>
	
	<!-- EN: left claw -->
	<Rotti.tools.0.label>左爪</Rotti.tools.0.label>
	
	<!-- EN: right claw -->
	<Rotti.tools.1.label>右爪</Rotti.tools.1.label>
	
	<!-- EN: head -->
	<Rotti.tools.3.label>腦袋</Rotti.tools.3.label>
	
</LanguageData>